sage_web_apps/__init__.py
sage_web_apps/run.py
sage_web_apps/sage_app.py
sage_web_apps/sage_input_app.py
sage_web_app-0.1.0.dist-info/METADATA
sage_web_app-0.1.0.dist-info/WHEEL
sage_web_app-0.1.0.dist-info/entry_points.txt
sage_web_app-0.1.0.dist-info/top_level.txt
sage_web_app-0.1.0.dist-info/RECORD
