Metadata-Version: 2.4
Name: sage-web-app
Version: 0.1.0
Summary: Web applications for Sage MS/MS search engine
Author-email: Patrick Garrett <pgarrett@scripps.edu>
Requires-Python: >=3.9
Requires-Dist: pandas
Requires-Dist: requests
Requires-Dist: streamlit
Requires-Dist: streamlit-permalink-pg
Provides-Extra: dev
Requires-Dist: pytest; extra == "dev"
Requires-Dist: black; extra == "dev"
